piscis/__init__.py
piscis/__main__.py
piscis/convert.py
piscis/core.py
piscis/data.py
piscis/downloads.py
piscis/losses.py
piscis/metrics.py
piscis/paths.py
piscis/training.py
piscis/transforms.py
piscis/utils.py
piscis/models/__init__.py
piscis/models/spots.py
piscis/networks/__init__.py
piscis/networks/conv.py
piscis/networks/efficientnetv2.py
piscis/networks/efficientnetv2_defaults.py
piscis/networks/fpn.py
piscis-1.0.0.dist-info/licenses/LICENSE
piscis-1.0.0.dist-info/METADATA
piscis-1.0.0.dist-info/WHEEL
piscis-1.0.0.dist-info/entry_points.txt
piscis-1.0.0.dist-info/top_level.txt
piscis-1.0.0.dist-info/RECORD
