Metadata-Version: 2.4
Name: Piscis
Version: 1.0.0
Summary: An automatic deep learning algorithm for spot detection in fluorescence microscopy images.
Author: William Niu
Author-email: wniu721@gmail.com
Keywords: machine learning,deep learning,spot detection,fluorescence microscopy
Classifier: Development Status :: 5 - Production/Stable
Classifier: Programming Language :: Python
Requires-Python: <4,>=3.7
License-File: LICENSE
Requires-Dist: deeptile
Requires-Dist: huggingface-hub
Requires-Dist: imageio
Requires-Dist: numba
Requires-Dist: numpy
Requires-Dist: opencv-python
Requires-Dist: pandas
Requires-Dist: scikit-image
Requires-Dist: scipy
Requires-Dist: torch
Requires-Dist: torchvision
Requires-Dist: tqdm
Requires-Dist: xarray
Dynamic: license-file
